Metadata-Version: 2.1
Name: pdxloc
Version: 0.0.1
Summary: An unoffical localization library for Paradox games
Author-email: Trym Bremnes <trym.bremnes@gmail.com>
License: Apache License 2.0
Project-URL: Homepage, https://github.com/trym-b/pdxloc
Project-URL: Bug Tracker, https://github.com/trym-b/pdxloc/issues
Classifier: Programming Language :: Python :: 3
Classifier: License :: OSI Approved :: Apache Software License
Classifier: Operating System :: OS Independent
Requires-Python: >=3.9
Provides-Extra: test
License-File: LICENSE
